aea_cli_benchmark/__init__.py
aea_cli_benchmark/core.py
aea_cli_benchmark/py.typed
aea_cli_benchmark/utils.py
aea_cli_benchmark/case_acn_communication/__init__.py
aea_cli_benchmark/case_acn_communication/case.py
aea_cli_benchmark/case_acn_communication/command.py
aea_cli_benchmark/case_acn_communication/utils.py
aea_cli_benchmark/case_acn_startup/__init__.py
aea_cli_benchmark/case_acn_startup/case.py
aea_cli_benchmark/case_acn_startup/command.py
aea_cli_benchmark/case_acn_startup/utils.py
aea_cli_benchmark/case_agent_construction_time/__init__.py
aea_cli_benchmark/case_agent_construction_time/case.py
aea_cli_benchmark/case_agent_construction_time/command.py
aea_cli_benchmark/case_decision_maker/__init__.py
aea_cli_benchmark/case_decision_maker/case.py
aea_cli_benchmark/case_decision_maker/command.py
aea_cli_benchmark/case_dialogues_memory_usage/__init__.py
aea_cli_benchmark/case_dialogues_memory_usage/case.py
aea_cli_benchmark/case_dialogues_memory_usage/command.py
aea_cli_benchmark/case_mem_usage/__init__.py
aea_cli_benchmark/case_mem_usage/case.py
aea_cli_benchmark/case_mem_usage/command.py
aea_cli_benchmark/case_messages_memory_usage/__init__.py
aea_cli_benchmark/case_messages_memory_usage/case.py
aea_cli_benchmark/case_messages_memory_usage/command.py
aea_cli_benchmark/case_multiagent/__init__.py
aea_cli_benchmark/case_multiagent/case.py
aea_cli_benchmark/case_multiagent/command.py
aea_cli_benchmark/case_multiagent_http_dialogues/__init__.py
aea_cli_benchmark/case_multiagent_http_dialogues/case.py
aea_cli_benchmark/case_multiagent_http_dialogues/command.py
aea_cli_benchmark/case_proactive/__init__.py
aea_cli_benchmark/case_proactive/case.py
aea_cli_benchmark/case_proactive/command.py
aea_cli_benchmark/case_reactive/__init__.py
aea_cli_benchmark/case_reactive/case.py
aea_cli_benchmark/case_reactive/command.py
aea_cli_benchmark/case_tx_generate/__init__.py
aea_cli_benchmark/case_tx_generate/case.py
aea_cli_benchmark/case_tx_generate/command.py
open_aea_cli_benchmark-2.0.8.dist-info/licenses/LICENSE
open_aea_cli_benchmark-2.0.8.dist-info/METADATA
open_aea_cli_benchmark-2.0.8.dist-info/WHEEL
open_aea_cli_benchmark-2.0.8.dist-info/entry_points.txt
open_aea_cli_benchmark-2.0.8.dist-info/top_level.txt
open_aea_cli_benchmark-2.0.8.dist-info/RECORD
